vocalocator/__init__.py
vocalocator/__main__.py
vocalocator/assess.py
vocalocator/calibration.py
vocalocator/update_json.py
vocalocator/util.py
vocalocator/architectures/__init__.py
vocalocator/architectures/base.py
vocalocator/architectures/ensemble.py
vocalocator/architectures/simplenet.py
vocalocator/architectures/simplenet_crosscorr.py
vocalocator/architectures/util.py
vocalocator/architectures/wavenet_arch.py
vocalocator/outputs/__init__.py
vocalocator/outputs/base.py
vocalocator/outputs/factory.py
vocalocator/outputs/gaussian.py
vocalocator/training/__init__.py
vocalocator/training/augmentations.py
vocalocator/training/configs.py
vocalocator/training/dataloaders.py
vocalocator/training/logger.py
vocalocator/training/losses.py
vocalocator/training/models.py
vocalocator/training/trainer.py
vocalocator-1.1.0.dist-info/METADATA
vocalocator-1.1.0.dist-info/WHEEL
vocalocator-1.1.0.dist-info/licenses/LICENSE
vocalocator-1.1.0.dist-info/RECORD
