Metadata-Version: 2.4
Name: vocalocator
Version: 1.1.0
Summary: Tool for sound-source localization of vocal calls
Project-URL: Homepage, https://github.com/neurostatslab/vocalocator
Project-URL: Issues, https://github.com/neurostatslab/vocalocator/issues
Author: NeuroStats Lab
License-Expression: MIT
License-File: LICENSE
Classifier: License :: OSI Approved :: MIT License
Classifier: Operating System :: OS Independent
Classifier: Programming Language :: Python :: 3
Requires-Python: >=3.9
Requires-Dist: h5py>=3.9.0
Requires-Dist: matplotlib>=3.8.0
Requires-Dist: numpy>=1.24.0
Requires-Dist: pyjson5>=1.6.0
Requires-Dist: scipy>=1.11.0
Requires-Dist: torch>=2.0.0
Requires-Dist: torchaudio>=2.0.0
Requires-Dist: tqdm>=4.66.0
